io/__init__.py
io/simulator.py
io/ur_rtde.py
motion/__init__.py
motion/executor.py
motion/planner.py
tests/__init__.py
tests/test_core.py
tools/__init__.py
tools/transforms.py
tools/utils.py
types/__init__.py
types/common_types.py
ur5lib-0.1.0.dist-info/METADATA
ur5lib-0.1.0.dist-info/WHEEL
ur5lib-0.1.0.dist-info/entry_points.txt
ur5lib-0.1.0.dist-info/top_level.txt
ur5lib-0.1.0.dist-info/RECORD
