Metadata-Version: 2.4
Name: ur5lib
Version: 0.1.0
Summary: Modular Python library for controlling a UR5 robot (real/sim)
Author: Masood Ahmad
Requires-Python: >=3.7
Requires-Dist: numpy
Requires-Dist: ur_rtde
Dynamic: requires-python
